[1,["ddxhC+hppCKqDDBVRMzdUY","c1U2WOc+9IaoL5vOUQ1Coh@f9941","88OQLRCCRIpq+3is6QbNyA@f9941","6akrtRDzlNvIjMHV0nb674","0fo8+6bxBNi54tPdCEFoRC@6c48a","7dj5uJT9FMn6OrOOx83tfK@f9941","d5ufc238REGK80yq6/jMNR@f9941","f82AaRK7ZAjIYtIjRW2Bbk@f9941","0fo8+6bxBNi54tPdCEFoRC@f9941","7b2rISLpdPpboGVI7hNYBj@f9941","36sDkPuydGXpA4EeCSyE9S@f9941","1dquJRG2RGwKW9cKOzfGdi@f9941","7b2rISLpdPpboGVI7hNYBj@6c48a","c1U2WOc+9IaoL5vOUQ1Coh@6c48a","d5ufc238REGK80yq6/jMNR@6c48a"],["node","_font","_spriteFrame","_textureSource","_parent","root","data"],[["cc.Widget",["_alignFlags","_left","_top","_originalWidth","_originalHeight","_bottom","_right","node","__prefab"],-4,1,4],["cc.Label",["_string","_actualFontSize","_fontSize","_isSystemFontUsed","_enableOutline","_lineHeight","_enableWrapText","_enableShadow","_shadowBlur","_overflow","_outlineWidth","node","__prefab","_outlineColor","_font","_color","_shadowColor","_shadowOffset"],-8,1,4,5,6,5,5,5],["cc.Node",["_name","_layer","_components","_prefab","_children","_parent","_lpos"],1,9,4,2,1,5],["cc.Sprite",["_sizeMode","_type","_isTrimmedMode","node","__prefab","_spriteFrame","_color"],0,1,4,6,5],"cc.SpriteFrame",["cc.Layout",["_resizeMode","_layoutType","_spacingX","_isAlign","_paddingTop","_paddingBottom","_spacingY","node","__prefab"],-4,1,4],["cc.UITransform",["node","__prefab","_contentSize","_anchorPoint"],3,1,4,5,5],["b444dDAGGJGtILm7em8LAWZ",["_transition","node","__prefab","clickEvents"],2,1,4,9],["cc.ClickEvent",["_componentId","handler","target"],1,1],["cc.Prefab",["_name"],2],["cc.CompPrefabInfo",["fileId"],2],["cc.BlockInputEvents",["node","__prefab"],3,1,4],["cc.PrefabInfo",["fileId","instance","targetOverrides","nestedPrefabInstanceRoots","root","asset"],-1,1,1]],[[10,0,2],[12,0,1,2,3,4,5,5],[6,0,1,2,1],[2,0,1,5,2,3,6,3],[6,0,1,2,3,1],[2,0,1,5,4,2,3,6,3],[2,0,1,5,2,3,3],[1,0,1,2,5,3,4,11,12,13,14,7],[0,0,1,7,8,3],[3,0,3,4,5,2],[1,0,1,2,3,4,11,12,13,14,6],[2,0,1,4,2,3,6,3],[5,0,1,2,3,7,8,5],[3,3,4,5,1],[7,0,1,2,3,2],[0,0,3,4,7,8,4],[0,0,1,6,3,7,8,5],[0,0,2,5,4,7,8,5],[8,1],[1,0,1,2,5,3,4,11,12,15,13,14,7],[1,0,1,2,5,6,3,4,7,8,11,12,13,16,17,14,10],[0,0,5,7,8,3],[0,0,1,2,7,8,4],[1,0,1,2,5,6,3,4,7,8,11,12,15,13,16,17,14,10],[9,0,2],[2,0,1,4,2,3,3],[2,0,1,5,4,2,3,3],[0,0,1,6,2,3,4,7,8,7],[0,2,7,8,2],[11,0,1,1],[5,0,1,4,5,6,7,8,6],[5,0,1,2,7,8,4],[3,1,0,2,3,4,5,4],[3,0,3,4,6,5,2],[3,1,0,3,4,5,3],[3,0,2,3,4,5,3],[7,0,1,2,2],[8,0,1,2,3],[1,0,1,2,5,9,3,4,11,12,13,14,8],[1,0,1,2,3,4,11,12,15,13,14,6],[1,0,1,2,6,3,4,10,11,12,13,14,8]],[[[{"name":"money_1","rect":{"x":1,"y":0,"width":84,"height":89},"offset":{"x":0,"y":0},"originalSize":{"width":86,"height":89},"rotated":false,"capInsets":[0,0,0,0],"vertices":{"rawPosition":[-42,-44.5,0,42,-44.5,0,-42,44.5,0,42,44.5,0],"indexes":[0,1,2,2,1,3],"uv":[1,89,85,89,1,0,85,0],"nuv":[0.011627906976744186,0,0.9883720930232558,0,0.011627906976744186,1,0.9883720930232558,1],"minPos":{"x":-42,"y":-44.5,"z":0},"maxPos":{"x":42,"y":44.5,"z":0}},"packable":true,"pixelsToUnit":100,"pivot":{"x":0.5,"y":0.5},"meshType":0}],[4],0,[0],[3],[4]],[[[24,"drawEarn"],[25,"drawEarn",33554432,[-5,-6],[[2,-2,[0,"a5KbFKeu1HF5OE38pxFNHA"],[5,750.0000000000001,1750]],[15,45,100,100,-3,[0,"f4wgKLx1ZKQoeoLNH8gCoB"]],[29,-4,[0,"c5ucdlb+9JtbvEdy0ItE1m"]]],[1,"94+CMNOnRGV5Wn6l7RHZVj",null,null,null,-1,0]],[11,"Layout",33554432,[-10,-11,-12,-13,-14],[[2,-7,[0,"8ebGXcqEZJSb/M7Cypj8DO"],[5,505.927734375,60]],[12,1,1,6,true,-8,[0,"c9BwDF03dHX6evKiLQMLX8"]],[21,4,189,-9,[0,"f2ZG8c7JdD07MPMo/VMLmp"]]],[1,"a7nxBwa3NDAYOvcBQ2C9nF",null,null,null,1,0],[1,0,-206.5,0]],[26,"drawRuleActionParent",33554432,1,[-16,-17,-18,-19,2,-20],[[2,-15,[0,"d3q/Yww4RCLar+QNqoYAkL"],[5,686,851]]],[1,"7fU2mKBn1FPrdhfWfGFPQJ",null,null,null,1,0]],[5,"content",33554432,3,[-25,-26,-27],[[4,-21,[0,"d6V747nCdFs7R/wqRXUkiT"],[5,614,508],[0,0.5,1]],[27,41,36,36,79,240,250,-22,[0,"8fDUIrYmpATbkPVFy0RzuJ"]],[30,1,2,32,48,64,-23,[0,"8ayZ2FZLdLvZ7NTbumPxxi"]],[32,1,0,false,-24,[0,"94MdTPL6RPYrB8fjO3gXEg"],30]],[1,"8eTNdi6cBLMJHorH6La8h+",null,null,null,1,0],[1,0,346.5,0]],[11,"Layout",33554432,[-31,-32,-33,-34],[[4,-28,[0,"54479g6cFN/IbvLc0rolw6"],[5,261.073828125,100],[0,0,0.25]],[12,1,1,6,true,-29,[0,"a1EWF4kAxGkqz4VEwHQCvT"]],[8,12,115,-30,[0,"f52GElJAJG5LdP5zUrCUvT"]]],[1,"16iN72gy1Jg4gxuv3R10TL",null,null,null,1,0],[1,-176,-25,0]],[11,"titleLayout",33554432,[-38,-39,-40,-41],[[4,-35,[0,"192y7dYdZNso2flGypud2y"],[5,309.7548828125,54.4],[0,0,0.5]],[31,1,1,6,-36,[0,"f4HkX276VFj4XI+iZJ2x9c"]],[8,9,115,-37,[0,"a5iK0QNXhMY6kbkkOLmoBe"]]],[1,"e62vlJ4kxN0aXrC9xDXtN8",null,null,null,1,0],[1,-176,22.8,0]],[11,"Layout",33554432,[-45,-46,-47,-48],[[4,-42,[0,"79aM6S0HlL2ZSr3Sq7JGpk"],[5,261.073828125,100],[0,0,0.25]],[12,1,1,6,true,-43,[0,"32LaG3JdlLE7sTFQ/lgEmL"]],[8,12,115,-44,[0,"87RiOiylNJVomjA71KGW1f"]]],[1,"b8yHmqe7BCrbzYO28S0c6L",null,null,null,1,0],[1,-176,-25,0]],[5,"earn1",33554432,4,[-51,-52,5,-53],[[2,-49,[0,"21BItvciJG1ZDxFQrjhsKg"],[5,582,100]],[16,40,16,16,100,-50,[0,"d1KJHX1hxEjo5XDU3/Cbfe"]]],[1,"63eg9KWuBLbawMjLk5tJML",null,null,null,1,0],[1,0,-82,0]],[5,"earn2",33554432,4,[-56,6,7,-57],[[2,-54,[0,"383ZasaaNCMLBtZO6CVTFd"],[5,582,100]],[16,40,16,16,100,-55,[0,"44d2mc669BZoi5C3F8uCYK"]]],[1,"ffckvLxNhOUqpj5wo8sDmv",null,null,null,1,0],[1,0,-246,0]],[5,"earn3",33554432,4,[-60,-61,-62,-63],[[2,-58,[0,"abDpHaIwZMkqlcRwLAhMNo"],[5,582,100]],[16,40,16,16,100,-59,[0,"62ZIIhvi1JBZw+E3TZg0GD"]]],[1,"68t6FgapNGjrGvVEkCccbj",null,null,null,1,0],[1,0,-410,0]],[5,"Node",33554432,8,[-68],[[2,-64,[0,"50K9GDfMBDqboxZ4/NU184"],[5,142,43]],[9,0,-65,[0,"53TNe+VfZAYIAlMPf6NgL3"],11],[14,3,-66,[0,"d4QSDBhVFLKJvg/Ckjt+1M"],[[18]]],[17,36,48.239000000000004,8,43,-67,[0,"06Pmeea99MbraV2jGgg5D6"]]],[1,"07kqCVvW9KF5Xjlrlok3vH",null,null,null,1,0],[1,220,-20.5,0]],[5,"Node",33554432,9,[-73],[[2,-69,[0,"7bNls8UF5PpKQONLMzS5G6"],[5,142,43]],[9,0,-70,[0,"b77O7GQyRAA7Up4Tf7IkwM"],22],[14,3,-71,[0,"f9DRlMNCxPUaj1+TvUVW0Q"],[[18]]],[17,36,48.239000000000004,8,43,-72,[0,"94uGUT5wRFxaZ+KgE4j94u"]]],[1,"20DeEj0fJIVrQ+e2YPIhFU",null,null,null,1,0],[1,220,-20.5,0]],[5,"Layout",33554432,10,[-77,-78],[[4,-74,[0,"a5MDrs85BKeLfmHrEF71Sn"],[5,98.388671875,100],[0,0,0.25]],[12,1,1,6,true,-75,[0,"4b9PGON8xKl6kk4gKg09EK"]],[8,12,115,-76,[0,"6ejji76KxEVLzx55m1SRsN"]]],[1,"93L/ioL3dKLZC3ns+pjSLp",null,null,null,1,0],[1,-176,-25,0]],[5,"Node",33554432,10,[-83],[[2,-79,[0,"a458GVU05P2ZV6ZqqzSlNx"],[5,142,43]],[9,0,-80,[0,"fbzbjlN6lCcJmzd9js8FwW"],29],[14,3,-81,[0,"645TCmbm1Oapm1GiiTuB7n"],[[18]]],[17,36,48.239000000000004,8,43,-82,[0,"1c+oh24pdKR5HBeHSJCkhA"]]],[1,"5erDySx3pBvaKgamRvP4C+",null,null,null,1,0],[1,220,-20.5,0]],[5,"customButtom",33554432,3,[-88],[[2,-84,[0,"86nUIG2fxHxoJQuU+Nq4uG"],[5,285,89]],[36,3,-85,[0,"b9zwa6JedCsJ50zw9+RRAF"]],[9,0,-86,[0,"8bqTzME8hPmZ3E1FvGjoSx"],38],[21,4,61,-87,[0,"53DZohq+1CZ4kG7T7jdQl4"]]],[1,"11uIw71A9EiKoaGBtZxfE9",null,null,null,1,0],[1,0,-320,0]],[5,"img_titleBg",33554432,3,[-92],[[2,-89,[0,"8crW9swr9GD5y6wcvCLI1K"],[5,460,152]],[13,-90,[0,"43PQStIVpI64Zzlv+HGF8h"],3],[28,-85,-91,[0,"26fTthr55Inp6yM9HqmzXy"]]],[1,"81iCTTZcNNtaP7cF20FD/k",null,null,null,1,0],[1,0,434.5,0]],[5,"earnItem",33554432,8,[-96],[[2,-93,[0,"98jQJvulVCXIpPZYnM/tR7"],[5,106,107]],[13,-94,[0,"3aZilM4hlA76IZWqYdmgZW"],4],[8,10,8,-95,[0,"c8GKBMROpEtIdyxyKDPq7A"]]],[1,"975xJdRpFPL6raYakXzXFh",null,null,null,1,0],[1,-230,0,0]],[5,"earnItem",33554432,9,[-100],[[2,-97,[0,"8eLih12tJJhJTnLFFtHftm"],[5,106,107]],[13,-98,[0,"86SVekgNJL/I/G93OpO27d"],12],[8,10,8,-99,[0,"40TRIhxzdFO4i9nDnbWa3w"]]],[1,"baKHliQkdEuoZy+vfQzltH",null,null,null,1,0],[1,-230,0,0]],[5,"earnItem",33554432,10,[-104],[[2,-101,[0,"7a0o+LsU1K7bePPSGbij3p"],[5,106,107]],[13,-102,[0,"d7ZRTjEUdMBZh8+qrLZsiE"],24],[8,10,8,-103,[0,"245UlVmXVB776Yeti+cc8U"]]],[1,"0cA2r1cL5D0ZHYNqF1Q7/U",null,null,null,1,0],[1,-230,0,0]],[6,"bg",33554432,1,[[2,-105,[0,"abe7OQN4xA1LMQTNy00Dv7"],[5,750.0000000000001,1750]],[33,0,-106,[0,"4fBu/yaXxGUb3f9og4qTXF"],[4,2516582400],0],[15,45,100,100,-107,[0,"c9CHf4DstN37ZuY/pl8lYr"]]],[1,"ffQLW6A/ZDVp/P0WNG63wq",null,null,null,1,0]],[6,"bg",33554432,3,[[2,-108,[0,"abqMv8gTpMDKnbzKR2XUrn"],[5,686,851]],[9,0,-109,[0,"32LQiVmN1Jf6VArFKIgi6q"],1],[15,45,100,100,-110,[0,"f5Y7wY7oNEU6ZJJPi7wup2"]]],[1,"1a/sKC2FtA6qYjT8LhoIW0",null,null,null,1,0]],[3,"title",33554432,8,[[4,-111,[0,"deM8R5AQ1N4ow1COyi7hu8"],[5,366.8701171875,54.4],[0,0,0.5]],[10,"Invite & Complete First Draw",26,26,false,true,-112,[0,"3alhiinh1CfYxewux+vKpL"],[4,637534208],5],[22,9,115,-2,-113,[0,"aeKpqR7XVOzL4/mR8BVUT6"]]],[1,"07w1nr7btCOYRQtZdg11Ac",null,null,null,1,0],[1,-176,24.8,0]],[5,"small",33554432,5,[-116],[[2,-114,[0,"9bTcxVZMdM071nN0cNsd2l"],[5,50.15,50.62]],[9,0,-115,[0,"93vNeib25EspFQeuBIW3nq"],7]],[1,"afaWffAN1MsImg0JB7txhE",null,null,null,1,0],[1,132.549609375,0,0]],[5,"small",33554432,7,[-119],[[2,-117,[0,"90n+Qf9F1LRb3iCuodfEXv"],[5,50.15,50.62]],[9,0,-118,[0,"f8GpHm7jZF954rsaskwFu6"],18]],[1,"1f9YDvMPpPk6KPRO+5KKMN",null,null,null,1,0],[1,132.549609375,0,0]],[3,"title",33554432,10,[[4,-120,[0,"9ezppxB4NEp6VR4KKxxzQb"],[5,198.2509765625,54.4],[0,0,0.5]],[10,"Purchase Times",26,26,false,true,-121,[0,"46BB0HzCBJQ6Ey+nlYBVjD"],[4,637534208],25],[22,9,115,-2,-122,[0,"24YxCr+ZtKdYIzEQyFRksX"]]],[1,"70+wvkDLNHYJL/fjDzb/dI",null,null,null,1,0],[1,-176,24.8,0]],[3,"xBtn",33554432,3,[[2,-123,[0,"b2gWif1uBM25v0W/hq4HV+"],[5,62,64]],[34,1,0,-124,[0,"cdlBlkvz9NZLXi8NbjXsDL"],31],[14,3,-125,[0,"3ba1FelL9CC5J+8AcL0iSk"],[[37,"fedd8P5qAtDR4GSaMXmVZis","destroySelf",1]]]],[1,"4aC9kYJVZPRbhDeEz7qwkg",null,null,null,1,0],[1,326,414.5,0]],[3,"title",33554432,16,[[2,-126,[0,"cbt51k9K1Pl4r2SGXrr0Dr"],[5,400,79.6]],[38,"Earn Chances",52,60,60,2,false,true,-127,[0,"3bf8IG2HRCKr/OtVlz2oRh"],[4,637534208],2]],[1,"d8XNmXzP1Nn51kWjrI5rM/",null,null,null,1,0],[1,0,16,0]],[6,"lab1",33554432,5,[[4,-128,[0,"663wrsRI1CroqnvlPt6S22"],[5,101.474609375,44.32],[0,0,0.5]],[7,"Reward",26,26,32,false,true,-129,[0,"a0WhGFUpJCsYOW3w9p0TqJ"],[4,637534208],6]],[1,"cdhnZK0jRHcab4451dDpGS",null,null,null,1,0]],[3,"rewardCount1",33554432,5,[[4,-130,[0,"92QqEe/CBJJbwvSs6sQ3SS"],[5,14.78125,44.32],[0,0,0.5]],[19,"1",32,32,32,false,true,-131,[0,"7a9U3i6X5AuYHY3TNB7MHg"],[4,4278190335],[4,637534208],8]],[1,"febzdAFeBCqrveMcvMSSsC",null,null,null,1,0],[1,163.62460937499998,0,0]],[3,"lab2",33554432,5,[[4,-132,[0,"f7ZvRzP3ZMbZZ0fIUlQR8b"],[5,76.66796875,44.32],[0,0,0.5]],[7,"Times",26,26,32,false,true,-133,[0,"28mr3s9+NItLURLXdn275A"],[4,637534208],9]],[1,"e2YglKmrNHjYw0DzFB4mhe",null,null,null,1,0],[1,184.40585937499998,0,0]],[6,"lab",33554432,11,[[2,-134,[0,"0eA3x5zFFNaYXF09AxudXm"],[5,106.763671875,29.2]],[7,"Invite Now",20,20,0,false,true,-135,[0,"52497ex5pMuZmB1ztZytgL"],[4,637534208],10]],[1,"1fbPRnt55NEYiDL4u2b7Rx",null,null,null,1,0]],[3,"title",33554432,6,[[4,-136,[0,"18uFuHHztNl5oHGjofzdc1"],[5,126.712890625,54.4],[0,0,0.5]],[10,"Complete",26,26,false,true,-137,[0,"31vnbBo2NLq6TuBRiqI1/B"],[4,637534208],13]],[1,"a9lqURc99GDKF38eWBDT/V",null,null,null,1,0],[1,0,2,0]],[3,"curCount",33554432,6,[[4,-138,[0,"cdDIaLrEBBUbcq9YK569vj"],[5,18.37109375,54.4],[0,0,0.5]],[39,"2",26,26,false,true,-139,[0,"4b+4PMrnZGV4x01NO8V5tj"],[4,4278190335],[4,637534208],14]],[1,"e76+XAcxBN2ZY8mOxmDZ2q",null,null,null,1,0],[1,132.712890625,2,0]],[3,"lab2",33554432,6,[[4,-140,[0,"e2qTI1vwpOMrtIb1u2F7Gq"],[5,87.865234375,54.4],[0,0,0.5]],[10,"Invites",26,26,false,true,-141,[0,"c54eKOdINHm4kMZxoN7FI4"],[4,637534208],15]],[1,"c7BNvuSYRO854OxMOcDa89",null,null,null,1,0],[1,157.083984375,2,0]],[3,"total",33554432,6,[[4,-142,[0,"f3tvzIb2VKCJEkJW2hvdwG"],[5,58.8056640625,54.4],[0,0,0.5]],[10,"(1/5)",26,26,false,true,-143,[0,"70IVtSitpBT7WfZDKpjk62"],[4,637534208],16]],[1,"11c5Kb0XFE/4hAnXCKhDzh",null,null,null,1,0],[1,250.94921875,2,0]],[6,"lab1",33554432,7,[[4,-144,[0,"d5u9AEYEZHw4ZRObQ2x82z"],[5,101.474609375,44.32],[0,0,0.5]],[7,"Reward",26,26,32,false,true,-145,[0,"9eWxod9TZNJ7BFxS/Jq//+"],[4,637534208],17]],[1,"6eF2Iu5b5L0L/L1CWq3KOT",null,null,null,1,0]],[3,"rewardCount2",33554432,7,[[4,-146,[0,"4cgdRtSfBKpaCBPoQ3r6is"],[5,14.78125,44.32],[0,0,0.5]],[19,"1",32,32,32,false,true,-147,[0,"268dhnqEFEEajf3dnhWuB8"],[4,4278190335],[4,637534208],19]],[1,"92SG9npwFJIZJvNJqPwuJH",null,null,null,1,0],[1,163.62460937499998,0,0]],[3,"lab2",33554432,7,[[4,-148,[0,"e2v4w1KdVAMrBrlU4Z2u+h"],[5,76.66796875,44.32],[0,0,0.5]],[7,"Times",26,26,32,false,true,-149,[0,"83lulU5uVK9oodudLO+7rU"],[4,637534208],20]],[1,"a25mw7lRFCjqDxDbWkxVrE",null,null,null,1,0],[1,184.40585937499998,0,0]],[6,"lab",33554432,12,[[2,-150,[0,"a0Bgz7au9BuaIWFJZF3bzF"],[5,106.763671875,29.2]],[7,"Invite Now",20,20,0,false,true,-151,[0,"aauP7+0GxDw6dUfee2ZOcO"],[4,637534208],21]],[1,"7a/to7GENL/IwgCwP79hw5",null,null,null,1,0]],[5,"Node",33554432,19,[-153],[[2,-152,[0,"46hI2ih/dJYJp+0Ebsrv9t"],[5,70,70]]],[1,"88x8fzFblEOZd0jU00N9VX",null,null,null,1,0],[1,-0.5,6,0]],[6,"money_1",33554432,40,[[2,-154,[0,"93NwvtYRREbrc62PnuF47L"],[5,81.7,84.55]],[35,0,false,-155,[0,"1ciWiMfNdNEI8fs8NNDn8g"],23]],[1,"46UyS4DgxPY7KLXh03ejMj",null,null,null,1,0]],[6,"lab1",33554432,13,[[4,-156,[0,"5am6IXkB9ETr2gEAT4FsjP"],[5,77.607421875,44.32],[0,0,0.5]],[7,"Limit:",26,26,32,false,true,-157,[0,"6155evUApDS4EcNTu+OFzK"],[4,637534208],26]],[1,"bed8xwHlpMlJGVuJOu6Ggu",null,null,null,1,0]],[3,"rewardCount3",33554432,13,[[4,-158,[0,"3e4D3Edm1OSrzyiNv4PM6q"],[5,14.78125,44.32],[0,0,0.5]],[19,"1",32,32,32,false,true,-159,[0,"d6f8EvLDxDdJHozNyKAAHD"],[4,4278190335],[4,637534208],27]],[1,"2aNrIx6hdKIb9IgHfhOOzm",null,null,null,1,0],[1,83.607421875,0,0]],[6,"lab",33554432,14,[[2,-160,[0,"9bY8uo9klHE4tXEwgp+1li"],[5,41.4609375,29.2]],[7,"Buy",20,20,0,false,true,-161,[0,"8eg8XMueFPp7JoXVa/TPLY"],[4,637534208],28]],[1,"dbvioUzrZFvKzMSJ0Q4C6a",null,null,null,1,0]],[3,"Label",33554432,2,[[2,-162,[0,"4fwdzOGydHNJmb4NvS+/w2"],[5,76.984375,44.32]],[20,"Only",32,32,0,false,false,true,true,6.8,-163,[0,"34b7S6qv5CTqV6Kq9Uvg46"],[4,637534208],[4,2147483648],[0,0,-2],32]],[1,"08MxB7ERBILZ2XKK0SDO+E",null,null,null,1,0],[1,-214.4716796875,0,0]],[3,"time",33554432,2,[[2,-164,[0,"8109RQOuBHlIqUnFjO4fMz"],[5,33.6015625,49.36]],[23,"{}",36,36,0,false,false,true,true,6.8,-165,[0,"6eGM1PCoRKQL9a2LoDBTp9"],[4,4278190335],[4,637534208],[4,2147483648],[0,0,-2],33]],[1,"90pmGdO85Jw65VXutUuIbh",null,null,null,1,0],[1,-153.1787109375,0,0]],[3,"Label-002",33554432,2,[[2,-166,[0,"22/0sUhd5EM7AK/HzQFbqE"],[5,173.9375,44.32]],[20,"left to give",32,32,0,false,false,true,true,6.8,-167,[0,"26PZ117OhHx7emKvuxPP81"],[4,637534208],[4,2147483648],[0,0,-2],34]],[1,"57akbd3l9BgYx5sAmy5TNJ",null,null,null,1,0],[1,-43.4091796875,0,0]],[3,"count",33554432,2,[[2,-168,[0,"96G7UVU7JPZqcMWXqC3BW7"],[5,107.482421875,49.36]],[23,"count",36,36,0,false,false,true,true,6.8,-169,[0,"5bBRQMFbNFE43AOwxqhMjt"],[4,4278190335],[4,637534208],[4,2147483648],[0,0,-2],35]],[1,"caD56XGdZHOZhLW0Gcu2OD",null,null,null,1,0],[1,103.30078125,0,0]],[3,"Label-004",33554432,2,[[2,-170,[0,"797FHnOyJGGIcjcGJ53dlF"],[5,89.921875,44.32]],[20,"times",32,32,0,false,false,true,true,6.8,-171,[0,"765IGlQcZM5pPurkkHsFW0"],[4,637534208],[4,2147483648],[0,0,-2],36]],[1,"6aGEpmpnZDza9zMRaqZwu9",null,null,null,1,0],[1,208.0029296875,0,0]],[6,"Label",33554432,15,[[2,-172,[0,"1bbG1Bzs1LboSxus7GtZB0"],[5,158.11416015625,58]],[40,"Co Draw",33,33,false,false,true,3.8,-173,[0,"1fzvC92StLJb0mllG0SBnx"],[4,1073741824],37]],[1,"ffZBPrI25L+q7bp2zxU9Qz",null,null,null,1,0]],[3,"Node",33554432,17,[[2,-174,[0,"b1PXyoVTtDkqVfi3QUNW1X"],[5,70,70]]],[1,"43M4pAT85EHqDig6wvSCsN",null,null,null,1,0],[1,-0.5,6,0]],[3,"Node",33554432,23,[[2,-175,[0,"52691y60BGz555fUTBRoSy"],[5,70,70]]],[1,"e01GjyrHFDZaUGeSVQfRNx",null,null,null,1,0],[1,-0.5,6,0]],[3,"Node",33554432,18,[[2,-176,[0,"d5L6As/bxJZ4Eu9+SxsF0O"],[5,70,70]]],[1,"28Gv02DWlGUYmmJn+TUlDF",null,null,null,1,0],[1,-0.5,6,0]],[3,"Node",33554432,24,[[2,-177,[0,"bceBjJqahC9oiMtTiyO4L8"],[5,70,70]]],[1,"07wX3NIvtFlpLiRFxTG2Jr",null,null,null,1,0],[1,-0.5,6,0]]],0,[0,5,1,0,0,1,0,0,1,0,0,1,0,-1,20,0,-2,3,0,0,2,0,0,2,0,0,2,0,-1,45,0,-2,46,0,-3,47,0,-4,48,0,-5,49,0,0,3,0,-1,21,0,-2,16,0,-3,4,0,-4,26,0,-6,15,0,0,4,0,0,4,0,0,4,0,0,4,0,-1,8,0,-2,9,0,-3,10,0,0,5,0,0,5,0,0,5,0,-1,28,0,-2,23,0,-3,29,0,-4,30,0,0,6,0,0,6,0,0,6,0,-1,32,0,-2,33,0,-3,34,0,-4,35,0,0,7,0,0,7,0,0,7,0,-1,36,0,-2,24,0,-3,37,0,-4,38,0,0,8,0,0,8,0,-1,17,0,-2,22,0,-4,11,0,0,9,0,0,9,0,-1,18,0,-4,12,0,0,10,0,0,10,0,-1,19,0,-2,25,0,-3,13,0,-4,14,0,0,11,0,0,11,0,0,11,0,0,11,0,-1,31,0,0,12,0,0,12,0,0,12,0,0,12,0,-1,39,0,0,13,0,0,13,0,0,13,0,-1,42,0,-2,43,0,0,14,0,0,14,0,0,14,0,0,14,0,-1,44,0,0,15,0,0,15,0,0,15,0,0,15,0,-1,50,0,0,16,0,0,16,0,0,16,0,-1,27,0,0,17,0,0,17,0,0,17,0,-1,51,0,0,18,0,0,18,0,0,18,0,-1,53,0,0,19,0,0,19,0,0,19,0,-1,40,0,0,20,0,0,20,0,0,20,0,0,21,0,0,21,0,0,21,0,0,22,0,0,22,0,0,22,0,0,23,0,0,23,0,-1,52,0,0,24,0,0,24,0,-1,54,0,0,25,0,0,25,0,0,25,0,0,26,0,0,26,0,0,26,0,0,27,0,0,27,0,0,28,0,0,28,0,0,29,0,0,29,0,0,30,0,0,30,0,0,31,0,0,31,0,0,32,0,0,32,0,0,33,0,0,33,0,0,34,0,0,34,0,0,35,0,0,35,0,0,36,0,0,36,0,0,37,0,0,37,0,0,38,0,0,38,0,0,39,0,0,39,0,0,40,0,-1,41,0,0,41,0,0,41,0,0,42,0,0,42,0,0,43,0,0,43,0,0,44,0,0,44,0,0,45,0,0,45,0,0,46,0,0,46,0,0,47,0,0,47,0,0,48,0,0,48,0,0,49,0,0,49,0,0,50,0,0,50,0,0,51,0,0,52,0,0,53,0,0,54,0,6,1,2,4,3,5,4,8,6,4,9,7,4,9,177],[0,0,0,0,0,0,0,0,0,0,0,0,0,0,0,0,0,0,0,0,0,0,0,0,0,0,0,0,0,0,0,0,0,0,0,0,0,0,0],[2,2,1,2,2,1,1,2,1,1,1,2,2,1,1,1,1,1,2,1,1,1,2,2,2,1,1,1,1,2,2,2,1,1,1,1,1,1,2],[5,6,3,7,1,0,0,1,0,0,0,2,1,0,0,0,0,0,1,0,0,0,2,8,1,0,0,0,0,2,9,10,0,0,0,0,0,3,11]],[[{"name":"BG2","rect":{"x":1,"y":0,"width":598,"height":641},"offset":{"x":0.5,"y":0},"originalSize":{"width":599,"height":641},"rotated":false,"capInsets":[32,32,32,48],"vertices":{"rawPosition":[-299,-320.5,0,299,-320.5,0,-299,320.5,0,299,320.5,0],"indexes":[0,1,2,2,1,3],"uv":[1,641,599,641,1,0,599,0],"nuv":[0.001669449081803005,0,1,0,0.001669449081803005,1,1,1],"minPos":{"x":-299,"y":-320.5,"z":0},"maxPos":{"x":299,"y":320.5,"z":0}},"packable":true,"pixelsToUnit":100,"pivot":{"x":0.5,"y":0.5},"meshType":0}],[4],0,[0],[3],[12]],[[{"name":"earnItem","rect":{"x":1,"y":0,"width":106,"height":107},"offset":{"x":0.5,"y":0},"originalSize":{"width":107,"height":107},"rotated":false,"capInsets":[0,0,0,0],"vertices":{"rawPosition":[-53,-53.5,0,53,-53.5,0,-53,53.5,0,53,53.5,0],"indexes":[0,1,2,2,1,3],"uv":[1,107,107,107,1,0,107,0],"nuv":[0.009345794392523364,0,1,0,0.009345794392523364,1,1,1],"minPos":{"x":-53,"y":-53.5,"z":0},"maxPos":{"x":53,"y":53.5,"z":0}},"packable":true,"pixelsToUnit":100,"pivot":{"x":0.5,"y":0.5},"meshType":0}],[4],0,[0],[3],[13]],[[{"name":"BG1","rect":{"x":1,"y":0,"width":685,"height":851},"offset":{"x":0.5,"y":0},"originalSize":{"width":686,"height":851},"rotated":false,"capInsets":[48,48,48,60],"vertices":{"rawPosition":[-342.5,-425.5,0,342.5,-425.5,0,-342.5,425.5,0,342.5,425.5,0],"indexes":[0,1,2,2,1,3],"uv":[1,851,686,851,1,0,686,0],"nuv":[0.0014577259475218659,0,1,0,0.0014577259475218659,1,1,1],"minPos":{"x":-342.5,"y":-425.5,"z":0},"maxPos":{"x":342.5,"y":425.5,"z":0}},"packable":true,"pixelsToUnit":100,"pivot":{"x":0.5,"y":0.5},"meshType":0}],[4],0,[0],[3],[14]]]]
